FPGA/fsm/testbench_fsm/fsm1.v
`timescale 10ns/10ps
module finitesm(input x,mclk, output reg y,d1,d2);
reg q1,q2;
reg [10:0] delay;

always @(negedge mclk) begin
	d1<= (!q1 && x)||(q2 && x);
	d2<=(q1 && x) ||(q2 && x);
	y<= q2 && x;
end
always @(posedge mclk) begin
	q1 <= d1;
	q2 <= d2;
end
endmodule

FPGA/fsm/testbench_fsm/fsm_tb.v
`timescale 10ns/10ps
module fsm_tb();
reg X,CLK;
wire CL,Y,D1,D2;
initial begin
X=0;
CLK =0;
end
finitesm dut(.x(X),.mclk(CLK),.y(Y),.d1(D1),.d2(D2));//module finitesm(input x,output y,cl,output reg d1,d2)
initial begin
#9 X =1;
#10 X=1;
#10 X=1;
#10 X=1;
#10 X=1;
#10 X=0;
#10 X=1;
#10 X=1;
end

always 
#5 CLK = !CLK;

initial begin
$dumpfile("fsm_tb.vcd");
$dumpvars(1,fsm_tb);
$monitor($time,"  X=%b,Y = %b,D2 =%b,D1 =%b",X,Y,D2,D1);
end
initial
#100 $finish;

endmodule

FPGA/fsm/testbench_fsm/fsm_tb.vcd
$date
	Mon Jul 11 12:49:57 2022
$end
$version
	Icarus Verilog
$end
$timescale
	10ps
$end
$scope module fsm_tb $end
$var wire 1 ! Y $end
$var wire 1 " D2 $end
$var wire 1 # D1 $end
$var reg 1 $ CLK $end
$var reg 1 % X $end
$upscope $end
$enddefinitions $end
#0
$dumpvars
0%
0$
0#
0"
0!
$end
#5000
1$
#9000
1%
#10000
1#
0$
#15000
1$
#20000
1"
0#
0$
#25000
1$
#30000
1!
1#
0$
#35000
1$
#40000
0$
#45000
1$
#50000
0$
#55000
1$
#59000
0%
#60000
0!
0"
0#
0$
#65000
1$
#69000
1%
#70000
1#
0$
#75000
1$
#80000
1"
0#
0$
#85000
1$
#90000
1!
1#
0$
